README.rst
lc.py
setup.py
lc.egg-info/PKG-INFO
lc.egg-info/SOURCES.txt
lc.egg-info/dependency_links.txt
lc.egg-info/entry_points.txt
lc.egg-info/top_level.txt