Metadata-Version: 1.2
Name: lc
Version: 0.1
Summary: Beta reducer and shorthand representer for the λ-calculus
Home-page: https://github.com/jackrosenthal/lambdacalc
Author: Jack Rosenthal
Author-email: jack@rosenth.al
License: MIT
Keywords: lambda calculus teaching
Platform: UNKNOWN
Classifier: Development Status :: 3 - Alpha
Classifier: Intended Audience :: Education
Classifier: Topic :: Software Development :: Interpreters
Classifier: License :: OSI Approved :: MIT License
Classifier: Programming Language :: Python :: 3
Classifier: Programming Language :: Python :: 3.4
Classifier: Programming Language :: Python :: 3.5
Classifier: Programming Language :: Python :: 3.6
Requires-Python: >=3.4, <4
